{
  "type": "FeatureCollection",
  "features": [
    {
      "type": "Feature",
      "properties": {
        "name": "Мурманская обл."
      },
      "geometry": {
        "type": "Polygon",
        "coordinates": [
          [
            [
              30.69203194801625,
              69.83801169528277
            ],
            [
              30.83008338663558,
              69.58106021305525
            ],
            [
              30.038240701318898,
              69.65044878190662
            ],
            [
              29.974074132589465,
              69.41963605243188
            ],
            [
              29.545770703622708,
              69.31787184461677
            ],
            [
              29.016196219844346,
              69.01186183535984
            ],
            [
              28.365986815183902,
              68.90829623045079
            ],
            [
              28.748330991475086,
              68.8611004988314
            ],
            [
              28.441426929071554,
              68.53613411060934
            ],
            [
              28.645528931186448,
              68.17906955552166
            ],
            [
              29.3091965052036,
              68.06019331198883
            ],
            [
              29.98207479441288,
              67.66197245799344
            ],
            [
              29.110540888218083,
              66.92257946432247
            ],
            [
              29.372862718950415,
              66.65576616597394
            ],
            [
              31.61839095582428,
              66.62795701355174
            ],
            [
              31.665286028050787,
              66.50042221232138
            ],
            [
              31.891075016343336,
              66.39055532508084
            ],
            [
              32.37606329837888,
              66.35347006949218
            ],
            [
              32.555099740242724,
              66.48174081540705
            ],
            [
              33.084006687324234,
              66.55912435410389
            ],
            [
              33.52091155293374,
              66.71843005156848
            ],
            [
              34.43595329049256,
              66.55485256710486
            ],
            [
              36.649455345291045,
              66.27692579991782
            ],
            [
              38.25075774547062,
              66.0320859176862
            ],
            [
              39.51306801064817,
              66.15164200211143
            ],
            [
              40.451795003503435,
              66.40389649426413
            ],
            [
              40.97064492154803,
              66.67581865994401
            ],
            [
              41.29953696639171,
              66.91231296438565
            ],
            [
              41.28157737750945,
              67.20199820425262
            ],
            [
              41.01041853084723,
              67.66826029497142
            ],
            [
              39.50866087434525,
              68.24794958708111
            ],
            [
              35.700260894661966,
              69.21389734198863
            ],
            [
              35.18103502378213,
              69.20471713097064
            ],
            [
              33.54254693010941,
              69.31969801162029
            ],
            [
              33.03205181442419,
              69.79719996232666
            ],
            [
              31.833163926757038,
              69.96435288284059
            ],
            [
              31.71619958654361,
              69.71086612285814
            ],
            [
              30.573975234591245,
              69.88181860047641
            ],
            [
              30.69203194801625,
              69.83801169528277
            ]
          ]
        ]
      }
    }
  ]
}